aliyunsdkcomputenest/__init__.py
aliyunsdkcomputenest/endpoint.py
aliyunsdkcomputenest/request/__init__.py
aliyunsdkcomputenest/request/v20210601/CancelServiceUsageRequest.py
aliyunsdkcomputenest/request/v20210601/ChangeResourceGroupRequest.py
aliyunsdkcomputenest/request/v20210601/ContinueDeployServiceInstanceRequest.py
aliyunsdkcomputenest/request/v20210601/CreateServiceInstanceRequest.py
aliyunsdkcomputenest/request/v20210601/CreateServiceUsageRequest.py
aliyunsdkcomputenest/request/v20210601/DeleteServiceInstancesRequest.py
aliyunsdkcomputenest/request/v20210601/GenerateServicePolicyRequest.py
aliyunsdkcomputenest/request/v20210601/GetServiceEstimateCostRequest.py
aliyunsdkcomputenest/request/v20210601/GetServiceInstanceRequest.py
aliyunsdkcomputenest/request/v20210601/GetServiceProvisionsRequest.py
aliyunsdkcomputenest/request/v20210601/GetServiceTemplateParameterConstraintsRequest.py
aliyunsdkcomputenest/request/v20210601/ListServiceCategoriesRequest.py
aliyunsdkcomputenest/request/v20210601/ListServiceInstanceLogsRequest.py
aliyunsdkcomputenest/request/v20210601/ListServiceInstanceResourcesRequest.py
aliyunsdkcomputenest/request/v20210601/ListServiceInstancesRequest.py
aliyunsdkcomputenest/request/v20210601/ListServiceUsagesRequest.py
aliyunsdkcomputenest/request/v20210601/ListTagKeysRequest.py
aliyunsdkcomputenest/request/v20210601/ListTagValuesRequest.py
aliyunsdkcomputenest/request/v20210601/RestartServiceInstanceRequest.py
aliyunsdkcomputenest/request/v20210601/StartServiceInstanceRequest.py
aliyunsdkcomputenest/request/v20210601/StopServiceInstanceRequest.py
aliyunsdkcomputenest/request/v20210601/TagResourcesRequest.py
aliyunsdkcomputenest/request/v20210601/UnTagResourcesRequest.py
aliyunsdkcomputenest/request/v20210601/UpdateServiceInstanceSpecRequest.py
aliyunsdkcomputenest/request/v20210601/UpdateServiceUsageRequest.py
aliyunsdkcomputenest/request/v20210601/__init__.py
aliyun_python_sdk_computenest-1.0.3.dist-info/LICENSE
aliyun_python_sdk_computenest-1.0.3.dist-info/METADATA
aliyun_python_sdk_computenest-1.0.3.dist-info/WHEEL
aliyun_python_sdk_computenest-1.0.3.dist-info/top_level.txt
aliyun_python_sdk_computenest-1.0.3.dist-info/RECORD
